businessready/DNAC_assurance_tests.j2
businessready/DNAC_device.j2
businessready/DNAC_device_backplane.j2
businessready/DNAC_device_chassis.j2
businessready/DNAC_device_compliance.j2
businessready/DNAC_device_fan.j2
businessready/DNAC_device_health.j2
businessready/DNAC_device_insight_speed_duplex.j2
businessready/DNAC_device_insight_vlan.j2
businessready/DNAC_device_interface.j2
businessready/DNAC_device_module.j2
businessready/DNAC_device_other.j2
businessready/DNAC_device_poe.j2
businessready/DNAC_device_power.j2
businessready/DNAC_device_processor.j2
businessready/DNAC_device_stack.j2
businessready/DNAC_device_vlan.j2
businessready/DNAC_empty.j2
businessready/DNAC_flow_analysis.j2
businessready/DNAC_network_health.j2
businessready/DNAC_physical_topology.j2
businessready/DNAC_projects.j2
businessready/DNAC_rf_profiles.j2
businessready/DNAC_routing_topology.j2
businessready/DNAC_site_health.j2
businessready/DNAC_site_member.j2
businessready/DNAC_sites.j2
businessready/DNAC_swim.j2
businessready/DNAC_templates.j2
businessready/DNAC_vlan_topology.j2
businessready/DNAC_vlans.j2
businessready/IOS_empty.j2
businessready/IOS_learn_acl.j2
businessready/IOS_learn_arp.j2
businessready/IOS_learn_arp_statistics.j2
businessready/IOS_learn_bgp.j2
businessready/IOS_learn_dot1x.j2
businessready/IOS_learn_dot1x_sessions.j2
businessready/IOS_learn_hsrp.j2
businessready/IOS_learn_interface.j2
businessready/IOS_learn_lldp.j2
businessready/IOS_learn_lldp_interfaces.j2
businessready/IOS_learn_ntp.j2
businessready/IOS_learn_ntp_associations.j2
businessready/IOS_learn_ntp_unicast.j2
businessready/IOS_learn_ospf.j2
businessready/IOS_learn_routing.j2
businessready/IOS_learn_stp.j2
businessready/IOS_learn_stp_mstp.j2
businessready/IOS_learn_stp_rpvst.j2
businessready/IOS_learn_vlan.j2
businessready/IOS_learn_vrf.j2
businessready/IOS_show_cdp_neighbors.j2
businessready/IOS_show_cdp_neighbors_detail.j2
businessready/IOS_show_cdp_neighbors_detail_totals.j2
businessready-0.9.151.dist-info/LICENSE
businessready-0.9.151.dist-info/WHEEL
businessready-0.9.151.dist-info/METADATA
businessready-0.9.151.dist-info/RECORD
