Metadata-Version: 2.1
Name: businessready
Version: 0.9.151
Summary: Transform Cisco CLIs and APIs into Business Ready Documents
Home-page: https://github.com/automateyournetwork/business_ready
Author: John Capobianco
Author-email: ptcapo@gmail.com
Requires-Python: >=3.8,<4.0
Classifier: Programming Language :: Python :: 3
Classifier: Programming Language :: Python :: 3.10
Classifier: Programming Language :: Python :: 3.8
Classifier: Programming Language :: Python :: 3.9
Requires-Dist: Jinja2 (==2.11.2)
Requires-Dist: MarkupSafe (==2.0.1)
Requires-Dist: requests (>=2.27.1,<3.0.0)
Requires-Dist: urllib3 (>=1.26.8,<2.0.0)
Requires-Dist: xmltodict (>=0.12.0,<0.13.0)
Project-URL: Repository, https://github.com/automateyournetwork/business_ready
